{"chunk_definitions":[{"row":11,"row_count":1,"visible":true,"expansion_state":0,"options":{"engine":"r","label":"unnamed-chunk-9"},"document_id":"383BA2C6","chunk_id":"cbl242z8gfbvl","chunk_label":"unnamed-chunk-1"},{"row":16,"row_count":1,"visible":true,"expansion_state":0,"options":{"engine":"r","label":"unnamed-chunk-12"},"document_id":"383BA2C6","chunk_id":"c6n63xkbwgp26","chunk_label":"unnamed-chunk-2"},{"row":29,"row_count":1,"visible":true,"expansion_state":0,"options":{"engine":"r","label":"unnamed-chunk-14"},"document_id":"383BA2C6","chunk_id":"co6arptz2q8in","chunk_label":"unnamed-chunk-3"},{"row":42,"row_count":1,"visible":true,"expansion_state":0,"options":{"engine":"r","label":"unnamed-chunk-4"},"document_id":"383BA2C6","chunk_id":"ch51pg48dajrj","chunk_label":"unnamed-chunk-4"},{"row":47,"row_count":1,"visible":true,"expansion_state":0,"options":{"engine":"r","label":"unnamed-chunk-5"},"document_id":"383BA2C6","chunk_id":"cdk76g5pk3fng","chunk_label":"unnamed-chunk-5"},{"row":51,"row_count":1,"visible":true,"expansion_state":0,"options":{"engine":"r","label":"unnamed-chunk-6"},"document_id":"383BA2C6","chunk_id":"c3h4w0ze41hpp","chunk_label":"unnamed-chunk-6"},{"row":63,"row_count":1,"visible":true,"expansion_state":0,"options":{"engine":"r","label":"unnamed-chunk-7"},"document_id":"383BA2C6","chunk_id":"c7ms53p7zekct","chunk_label":"unnamed-chunk-7"},{"row":79,"row_count":1,"visible":true,"expansion_state":0,"options":{"engine":"r","label":"unnamed-chunk-8"},"document_id":"383BA2C6","chunk_id":"cw5okj9lpy7lv","chunk_label":"unnamed-chunk-8"},{"row":87,"row_count":1,"visible":true,"expansion_state":0,"options":{"engine":"r","label":"unnamed-chunk-18"},"document_id":"383BA2C6","chunk_id":"cr8712h4r6q7p","chunk_label":"unnamed-chunk-9"},{"row":93,"row_count":1,"visible":true,"expansion_state":0,"options":{"engine":"r","label":"unnamed-chunk-19"},"document_id":"383BA2C6","chunk_id":"cbuwlin6h560z","chunk_label":"unnamed-chunk-10"},{"row":102,"row_count":1,"visible":true,"expansion_state":0,"options":{"engine":"r","label":"unnamed-chunk-20"},"document_id":"383BA2C6","chunk_id":"cey2qq1z7e76g","chunk_label":"unnamed-chunk-11"},{"row":116,"row_count":1,"visible":true,"expansion_state":0,"options":{"engine":"r","label":"unnamed-chunk-21"},"document_id":"383BA2C6","chunk_id":"cgvq9zntgsmcs","chunk_label":"unnamed-chunk-12"},{"row":125,"row_count":1,"visible":true,"expansion_state":0,"options":{"engine":"r","label":"unnamed-chunk-22"},"document_id":"383BA2C6","chunk_id":"cc19w7qaf600y","chunk_label":"unnamed-chunk-13"},{"row":134,"row_count":1,"visible":true,"expansion_state":0,"options":{"engine":"r","label":"unnamed-chunk-23"},"document_id":"383BA2C6","chunk_id":"c27627pp5zt35","chunk_label":"unnamed-chunk-14"},{"row":161,"row_count":1,"visible":true,"expansion_state":0,"options":{"engine":"r","label":"unnamed-chunk-24"},"document_id":"383BA2C6","chunk_id":"c3zq6fazs5vpx","chunk_label":"unnamed-chunk-15"},{"row":177,"row_count":1,"visible":true,"expansion_state":0,"options":{"engine":"r","label":"unnamed-chunk-25"},"document_id":"383BA2C6","chunk_id":"c4ii0fnegv3qh","chunk_label":"unnamed-chunk-16"},{"row":189,"row_count":1,"visible":true,"expansion_state":0,"options":{"engine":"r","label":"unnamed-chunk-26"},"document_id":"383BA2C6","chunk_id":"c5rstc4ck9pam","chunk_label":"unnamed-chunk-17"},{"row":193,"row_count":1,"visible":true,"expansion_state":0,"options":{"engine":"r","label":"unnamed-chunk-27"},"document_id":"383BA2C6","chunk_id":"c8exdscxm9ypw","chunk_label":"unnamed-chunk-18"},{"row":199,"row_count":1,"visible":true,"expansion_state":0,"options":{"engine":"r","label":"unnamed-chunk-28"},"document_id":"383BA2C6","chunk_id":"cvvirvlu1wohj","chunk_label":"unnamed-chunk-19"},{"row":205,"row_count":1,"visible":true,"expansion_state":0,"options":{"engine":"r","label":"unnamed-chunk-29"},"document_id":"383BA2C6","chunk_id":"cyeg3fpxnt9gj","chunk_label":"unnamed-chunk-20"},{"row":209,"row_count":1,"visible":true,"expansion_state":0,"options":{"engine":"r","label":"unnamed-chunk-30"},"document_id":"383BA2C6","chunk_id":"cq359cp0hurxh","chunk_label":"unnamed-chunk-21"},{"row":230,"row_count":1,"visible":true,"expansion_state":0,"options":{"engine":"r","label":"unnamed-chunk-31"},"document_id":"383BA2C6","chunk_id":"cb3v6oji9v741","chunk_label":"unnamed-chunk-22"},{"row":235,"row_count":1,"visible":true,"expansion_state":0,"options":{"engine":"r","label":"unnamed-chunk-32"},"document_id":"383BA2C6","chunk_id":"ckhdfbpdm4hqv","chunk_label":"unnamed-chunk-23"},{"row":239,"row_count":1,"visible":true,"expansion_state":0,"options":{"engine":"r","label":"unnamed-chunk-129"},"document_id":"383BA2C6","chunk_id":"c8xsf98x7l851","chunk_label":"unnamed-chunk-24"}],"doc_write_time":1681855505}